{
  "iri": "fecc9738-3088-4ad4-98b1-4d7c2355a3d9",
  "projectIri": "8c23bccf-27fb-496f-a4f2-9f30375714e2",
  "types": [
    "https://dataspecer.com/core/model-descriptor/pim-store-wrapper"
  ],
  "userMetadata": {
    "documentBaseUrl": "https://datagov-cz.github.io/cache-slovniku/rdfs.ttl",
    "label": {
      "en": "rdfs"
    }
  },
  "metadata": {
    "creationDate": "2026-04-07T01:01:22.566Z",
    "modificationDate": "2026-04-07T01:03:01.690Z"
  },
  "_version": 1,
  "_exportVersion": 2,
  "_exportedAt": "2026-04-07T01:04:04.755Z",
  "_exportedBy": "http://localhost:3100"
}